{"1":[{"root":"قرع","lemma":"قارِعَة","pos":"noun"}],"2":[{"root":null,"lemma":"ما","pos":"noun"},{"root":"قرع","lemma":"قارِعَة","pos":"noun"}],"3":[{"root":null,"lemma":"ما","pos":"noun"},{"root":"دري","lemma":"أَدْرَى","pos":"verb"},{"root":null,"lemma":"ما","pos":"noun"},{"root":"قرع","lemma":"قارِعَة","pos":"noun"}],"4":[{"root":"يوم","lemma":"يَوْم","pos":"noun"},{"root":"كون","lemma":"كانَ","pos":"verb"},{"root":"أنس","lemma":"ناس","pos":"noun"},{"root":"فرش","lemma":"فَراش","pos":"noun"},{"root":"بثث","lemma":"مَبْثُوث","pos":"adjective"}],"5":[{"root":"كون","lemma":"كانَ","pos":"verb"},{"root":"جبل","lemma":"جَبَل","pos":"noun"},{"root":"عهن","lemma":"عِهْن","pos":"noun"},{"root":"نفش","lemma":"مَنفُوش","pos":"adjective"}],"6":[{"root":null,"lemma":"أَمّا","pos":"particle"},{"root":null,"lemma":"مَن","pos":"noun"},{"root":"ثقل","lemma":"ثَقُلَتْ","pos":"verb"},{"root":"وزن","lemma":"مِيزان","pos":"noun"}],"7":[{"root":null,"lemma":"ف","pos":"pronoun"},{"root":null,"lemma":"فِي","pos":"preposition"},{"root":"عيش","lemma":"عِيشَة","pos":"noun"},{"root":"رضو","lemma":"راضِيَة","pos":"adjective"}],"8":[{"root":null,"lemma":"أَمّا","pos":"particle"},{"root":null,"lemma":"مَن","pos":"noun"},{"root":"خفف","lemma":"خَفَّتْ","pos":"verb"},{"root":"وزن","lemma":"مِيزان","pos":"noun"}],"9":[{"root":"أمم","lemma":"أُمّ","pos":"noun"},{"root":"هوي","lemma":"هاوِيَة","pos":"active participle"}],"10":[{"root":null,"lemma":"ما","pos":"noun"},{"root":"دري","lemma":"أَدْرَى","pos":"verb"},{"root":null,"lemma":"ما","pos":"noun"},{"root":null,"lemma":null,"pos":"pronoun"}],"11":[{"root":"نور","lemma":"نار","pos":"noun"},{"root":"حمي","lemma":"حامِيَة","pos":"adjective"}]}